nacos/__init__.py
nacos/entities.py
nacos/errors.py
nacos/nacos.py
nacos/params.py
pynacos_sdk-0.4.1.dist-info/LICENSE
pynacos_sdk-0.4.1.dist-info/METADATA
pynacos_sdk-0.4.1.dist-info/WHEEL
pynacos_sdk-0.4.1.dist-info/top_level.txt
pynacos_sdk-0.4.1.dist-info/RECORD
