Metadata-Version: 2.1
Name: pynacos-sdk
Version: 0.4.1
Summary: Nacos sdk for python
Home-page: https://github.com/olivetree123/pynacos-sdk
Author: olivetree
Author-email: olivetree123@163.com
License: MIT
Platform: UNKNOWN
Requires-Dist: winney (>=0.5.0)
